django_dynaconf/__init__.py
django_dynaconf/admin.py
django_dynaconf/apps.py
django_dynaconf/configs.py
django_dynaconf/models.py
django_dynaconf/migrations/0001_initial.py
django_dynaconf/migrations/0002_auto_20230730_1449.py
django_dynaconf/migrations/__init__.py
django_dynaconf-1.3.1.dist-info/LICENSE
django_dynaconf-1.3.1.dist-info/METADATA
django_dynaconf-1.3.1.dist-info/WHEEL
django_dynaconf-1.3.1.dist-info/top_level.txt
django_dynaconf-1.3.1.dist-info/RECORD
