Metadata-Version: 2.1
Name: django-dynaconf
Version: 1.3.1
Summary: Dynamic Configuration for your Django project
Home-page: https://github.com/mhsiddiqui/django-dynaconf
Author: Muhammad Hassan Siddiqui
Author-email: mhassan.eeng@gmail.com
License: MIT
Keywords: django,dynamic-configuration,dynamic-settings,django-settings-from-admin
Platform: any
Classifier: Development Status :: 5 - Production/Stable
Classifier: Environment :: Web Environment
Classifier: Framework :: Django
Classifier: Framework :: Django :: 1.10
Classifier: Framework :: Django :: 2.2
Classifier: Framework :: Django :: 3.0
Classifier: Framework :: Django :: 3.1
Classifier: Framework :: Django :: 3.2
Classifier: Framework :: Django :: 4.0
Classifier: Framework :: Django :: 4.1
Classifier: Framework :: Django :: 4.2
Classifier: Intended Audience :: Developers
Classifier: License :: OSI Approved :: MIT License
Classifier: Natural Language :: English
Classifier: Operating System :: OS Independent
Classifier: Programming Language :: Python
Classifier: Programming Language :: Python :: 3.7
Classifier: Programming Language :: Python :: 3.8
Classifier: Programming Language :: Python :: 3.9
Classifier: Programming Language :: Python :: 3.10
Classifier: Programming Language :: Python :: 3.11
Classifier: Programming Language :: Python :: Implementation :: CPython
Classifier: Programming Language :: Python :: Implementation :: PyPy
Classifier: Topic :: Utilities
Requires-Python: >=3
License-File: LICENSE
Provides-Extra: dateutil
Requires-Dist: python-dateutil ; extra == 'dateutil'
Provides-Extra: django
Requires-Dist: Django >1.10 ; extra == 'django'
